{
  "deck_number": 3,
  "max_splits": 2,
  "dealer_hits_soft17": false,
  "dealer_peeks": false,
  "das": true,
  "allow_double": true,
  "allow_insurance": false,
  "allow_surrender": false,
  "burn_count": 1,
  "bankroll": 178928.83159097985,
  "unit_percent": 0.2,
  "cards_seen_counts": {
    "2": 9,
    "3": 12,
    "4": 9,
    "5": 11,
    "6": 12,
    "7": 12,
    "8": 12,
    "9": 12,
    "10": 44,
    "11": 11
  },
  "player_hands": [
    []
  ],
  "dealer_cards": [],
  "active_hand_index": 0,
  "session_stats": {
    "wins": 111,
    "losses": 143,
    "pushes": 74,
    "net_profit": -36065.9583525457,
    "history": [
      {
        "game": 1,
        "profit": 1434.6325,
        "win_rate": 1.0
      },
      {
        "game": 2,
        "profit": 6022.3822875,
        "win_rate": 1.0
      },
      {
        "game": 3,
        "profit": 9322.43412328125,
        "win_rate": 1.0
      },
      {
        "game": 4,
        "profit": 12746.237902904297,
        "win_rate": 1.0
      },
      {
        "game": 5,
        "profit": 16298.43432426321,
        "win_rate": 1.0
      },
      {
        "game": 6,
        "profit": 12613.03053710334,
        "win_rate": 0.8333333333333334
      },
      {
        "game": 7,
        "profit": 16160.231682244714,
        "win_rate": 0.8571428571428571
      },
      {
        "game": 8,
        "profit": 12480.010494160537,
        "win_rate": 0.75
      },
      {
        "game": 9,
        "profit": 8937.797600629518,
        "win_rate": 0.6666666666666666
      },
      {
        "game": 10,
        "profit": 12347.177510653124,
        "win_rate": 0.7
      },
      {
        "game": 11,
        "profit": 15884.409167302616,
        "win_rate": 0.7272727272727273
      },
      {
        "game": 12,
        "profit": 12214.531323528767,
        "win_rate": 0.6666666666666666
      },
      {
        "game": 13,
        "profit": 8682.273898896437,
        "win_rate": 0.6153846153846154
      },
      {
        "game": 14,
        "profit": 5282.476127687821,
        "win_rate": 0.5714285714285714
      },
      {
        "game": 15,
        "profit": 2010.170772899527,
        "win_rate": 0.5333333333333333
      },
      {
        "game": 16,
        "profit": 5159.76467688326,
        "win_rate": 0.5625
      },
      {
        "game": 17,
        "profit": 1892.061001500137,
        "win_rate": 0.5294117647058824
      },
      {
        "game": 18,
        "profit": -4398.268573612375,
        "win_rate": 0.5
      },
      {
        "game": 19,
        "profit": -1488.9911451228381,
        "win_rate": 0.5263157894736842
      },
      {
        "game": 20,
        "profit": 1529.3841869350567,
        "win_rate": 0.55
      },
      {
        "game": 21,
        "profit": 4660.948593945122,
        "win_rate": 0.5714285714285714
      },
      {
        "game": 22,
        "profit": 7909.946666218066,
        "win_rate": 0.5909090909090909
      },
      {
        "game": 23,
        "profit": 7235.77956622143,
        "win_rate": 0.5652173913043478
      },
      {
        "game": 24,
        "profit": 7012.742617305877,
        "win_rate": 0.5416666666666666
      },
      {
        "game": 25,
        "profit": 6790.263260762612,
        "win_rate": 0.52
      },
      {
        "game": 26,
        "profit": 7012.186418914519,
        "win_rate": 0.5384615384615384
      },
      {
        "game": 27,
        "profit": 6789.708452867232,
        "win_rate": 0.5185185185185185
      },
      {
        "game": 28,
        "profit": 7011.6302239994,
        "win_rate": 0.5357142857142857
      },
      {
        "game": 29,
        "profit": 6789.153648439402,
        "win_rate": 0.5172413793103449
      },
      {
        "game": 30,
        "profit": 6567.233264318304,
        "win_rate": 0.5
      },
      {
        "game": 31,
        "profit": 6788.598847479099,
        "win_rate": 0.5161290322580645
      },
      {
        "game": 32,
        "profit": 6888.598847479099,
        "win_rate": 0.53125
      },
      {
        "game": 33,
        "profit": 6788.598847479099,
        "win_rate": 0.5151515151515151
      },
      {
        "game": 34,
        "profit": 6688.598847479099,
        "win_rate": 0.5
      },
      {
        "game": 35,
        "profit": 6788.598847479099,
        "win_rate": 0.5142857142857142
      },
      {
        "game": 36,
        "profit": 6688.598847479099,
        "win_rate": 0.5
      },
      {
        "game": 37,
        "profit": 6888.598847479099,
        "win_rate": 0.5135135135135135
      },
      {
        "game": 38,
        "profit": 6988.598847479099,
        "win_rate": 0.5263157894736842
      },
      {
        "game": 39,
        "profit": 7088.598847479099,
        "win_rate": 0.5384615384615384
      },
      {
        "game": 40,
        "profit": 6988.598847479099,
        "win_rate": 0.525
      },
      {
        "game": 41,
        "profit": 7088.598847479099,
        "win_rate": 0.5365853658536586
      },
      {
        "game": 42,
        "profit": 6988.598847479099,
        "win_rate": 0.5238095238095238
      },
      {
        "game": 43,
        "profit": 7211.017844597797,
        "win_rate": 0.5348837209302325
      },
      {
        "game": 44,
        "profit": 5427.2174877058405,
        "win_rate": 0.5227272727272727
      },
      {
        "game": 45,
        "profit": 2149.48433191687,
        "win_rate": 0.5111111111111111
      },
      {
        "game": 46,
        "profit": 5304.302494363755,
        "win_rate": 0.5217391304347826
      },
      {
        "game": 47,
        "profit": 6177.135519307392,
        "win_rate": 0.5319148936170213
      },
      {
        "game": 48,
        "profit": 6277.135519307392,
        "win_rate": 0.5416666666666666
      },
      {
        "game": 49,
        "profit": 6056.495180509124,
        "win_rate": 0.5306122448979592
      },
      {
        "game": 50,
        "profit": 6276.583918460397,
        "win_rate": 0.54
      },
      {
        "game": 51,
        "profit": 6055.944958664246,
        "win_rate": 0.5294117647058824
      },
      {
        "game": 52,
        "profit": 5835.857596267585,
        "win_rate": 0.5192307692307693
      },
      {
        "game": 53,
        "profit": 5935.857596267585,
        "win_rate": 0.5283018867924528
      },
      {
        "game": 54,
        "profit": 6155.644740258254,
        "win_rate": 0.5370370370370371
      },
      {
        "game": 55,
        "profit": 4392.951845453088,
        "win_rate": 0.5272727272727272
      },
      {
        "game": 56,
        "profit": 3745.1622066121895,
        "win_rate": 0.5178571428571429
      },
      {
        "game": 57,
        "profit": 4388.093423161781,
        "win_rate": 0.5263157894736842
      },
      {
        "game": 58,
        "profit": 4155.998423161781,
        "win_rate": 0.5172413793103449
      },
      {
        "game": 59,
        "profit": 4387.513185661781,
        "win_rate": 0.5254237288135594
      },
      {
        "game": 60,
        "profit": 4487.513185661781,
        "win_rate": 0.5333333333333333
      },
      {
        "game": 61,
        "profit": 4387.513185661781,
        "win_rate": 0.5245901639344263
      },
      {
        "game": 62,
        "profit": 4487.513185661781,
        "win_rate": 0.532258064516129
      },
      {
        "game": 63,
        "profit": 4255.169636255531,
        "win_rate": 0.5238095238095238
      },
      {
        "game": 64,
        "profit": 4023.406945722797,
        "win_rate": 0.515625
      },
      {
        "game": 65,
        "profit": 3923.406945722797,
        "win_rate": 0.5076923076923077
      },
      {
        "game": 66,
        "profit": 3823.406945722797,
        "win_rate": 0.5
      },
      {
        "game": 67,
        "profit": 3638.860945722797,
        "win_rate": 0.4925373134328358
      },
      {
        "game": 68,
        "profit": 3454.6840377227973,
        "win_rate": 0.4852941176470588
      },
      {
        "game": 69,
        "profit": 3270.875483538797,
        "win_rate": 0.4782608695652174
      },
      {
        "game": 70,
        "profit": 3637.7573576900613,
        "win_rate": 0.4857142857142857
      },
      {
        "game": 71,
        "profit": 3453.582656866127,
        "win_rate": 0.4788732394366197
      },
      {
        "game": 72,
        "profit": 3269.77630544384,
        "win_rate": 0.4722222222222222
      },
      {
        "game": 73,
        "profit": 3369.77630544384,
        "win_rate": 0.4794520547945205
      },
      {
        "game": 74,
        "profit": 3269.77630544384,
        "win_rate": 0.47297297297297297
      },
      {
        "game": 75,
        "profit": 3169.77630544384,
        "win_rate": 0.4666666666666667
      },
      {
        "game": 76,
        "profit": 3269.77630544384,
        "win_rate": 0.47368421052631576
      },
      {
        "game": 77,
        "profit": 3169.77630544384,
        "win_rate": 0.4675324675324675
      },
      {
        "game": 78,
        "profit": 3069.77630544384,
        "win_rate": 0.46153846153846156
      },
      {
        "game": 79,
        "profit": 2969.77630544384,
        "win_rate": 0.45569620253164556
      },
      {
        "game": 80,
        "profit": 2786.937566724398,
        "win_rate": 0.45
      },
      {
        "game": 81,
        "profit": 3151.8836892084046,
        "win_rate": 0.4567901234567901
      },
      {
        "game": 82,
        "profit": 4251.101410130232,
        "win_rate": 0.4634146341463415
      },
      {
        "game": 83,
        "profit": 3694.897243343787,
        "win_rate": 0.4578313253012048
      },
      {
        "game": 84,
        "profit": 9223.566661201048,
        "win_rate": 0.4642857142857143
      },
      {
        "game": 85,
        "profit": 12153.761452665396,
        "win_rate": 0.47058823529411764
      },
      {
        "game": 86,
        "profit": 15171.862087873675,
        "win_rate": 0.47674418604651164
      },
      {
        "game": 87,
        "profit": 12063.218433609149,
        "win_rate": 0.47126436781609193
      },
      {
        "game": 88,
        "profit": 9047.834088972559,
        "win_rate": 0.4659090909090909
      },
      {
        "game": 89,
        "profit": 9242.828943259059,
        "win_rate": 0.47191011235955055
      },
      {
        "game": 90,
        "profit": 9342.828943259059,
        "win_rate": 0.4777777777777778
      },
      {
        "game": 91,
        "profit": 9442.828943259059,
        "win_rate": 0.4835164835164835
      },
      {
        "game": 92,
        "profit": 9542.828943259059,
        "win_rate": 0.4891304347826087
      },
      {
        "game": 93,
        "profit": 9642.828943259059,
        "win_rate": 0.4946236559139785
      },
      {
        "game": 94,
        "profit": 9542.828943259059,
        "win_rate": 0.48936170212765956
      },
      {
        "game": 95,
        "profit": 9642.828943259059,
        "win_rate": 0.49473684210526314
      },
      {
        "game": 96,
        "profit": 9542.828943259059,
        "win_rate": 0.4895833333333333
      },
      {
        "game": 97,
        "profit": 9442.828943259059,
        "win_rate": 0.4845360824742268
      },
      {
        "game": 98,
        "profit": 9342.828943259059,
        "win_rate": 0.47959183673469385
      },
      {
        "game": 99,
        "profit": 9442.828943259059,
        "win_rate": 0.48484848484848486
      },
      {
        "game": 100,
        "profit": 9342.828943259059,
        "win_rate": 0.48
      },
      {
        "game": 101,
        "profit": 9442.828943259059,
        "win_rate": 0.48514851485148514
      },
      {
        "game": 102,
        "profit": 9342.828943259059,
        "win_rate": 0.4803921568627451
      },
      {
        "game": 103,
        "profit": 9242.828943259059,
        "win_rate": 0.47572815533980584
      },
      {
        "game": 104,
        "profit": 9142.828943259059,
        "win_rate": 0.47115384615384615
      },
      {
        "game": 105,
        "profit": 9042.828943259059,
        "win_rate": 0.4666666666666667
      },
      {
        "game": 106,
        "profit": 9142.828943259059,
        "win_rate": 0.4716981132075472
      },
      {
        "game": 107,
        "profit": 9042.828943259059,
        "win_rate": 0.4672897196261682
      },
      {
        "game": 108,
        "profit": 9142.828943259059,
        "win_rate": 0.4722222222222222
      },
      {
        "game": 109,
        "profit": 9042.828943259059,
        "win_rate": 0.46788990825688076
      },
      {
        "game": 110,
        "profit": 8942.828943259059,
        "win_rate": 0.4636363636363636
      },
      {
        "game": 111,
        "profit": 9042.828943259059,
        "win_rate": 0.46846846846846846
      },
      {
        "game": 112,
        "profit": 8842.828943259059,
        "win_rate": 0.4642857142857143
      },
      {
        "game": 113,
        "profit": 9042.42894325906,
        "win_rate": 0.4690265486725664
      },
      {
        "game": 114,
        "profit": 8842.42974325906,
        "win_rate": 0.4649122807017544
      },
      {
        "game": 115,
        "profit": 9042.02894485906,
        "win_rate": 0.46956521739130436
      },
      {
        "game": 116,
        "profit": 9242.02734486226,
        "win_rate": 0.47413793103448276
      },
      {
        "game": 117,
        "profit": 9442.425741665465,
        "win_rate": 0.47863247863247865
      },
      {
        "game": 118,
        "profit": 9643.224935262278,
        "win_rate": 0.4830508474576271
      },
      {
        "game": 119,
        "profit": 9844.425727246286,
        "win_rate": 0.48739495798319327
      },
      {
        "game": 120,
        "profit": 9642.82253367831,
        "win_rate": 0.48333333333333334
      },
      {
        "game": 121,
        "profit": 9441.622546497472,
        "win_rate": 0.4793388429752066
      },
      {
        "game": 122,
        "profit": 9642.420133703949,
        "win_rate": 0.48360655737704916
      },
      {
        "game": 123,
        "profit": 9441.22095132306,
        "win_rate": 0.4796747967479675
      },
      {
        "game": 124,
        "profit": 9039.627383290803,
        "win_rate": 0.47580645161290325
      },
      {
        "game": 125,
        "profit": 10239.588964571183,
        "win_rate": 0.48
      },
      {
        "game": 126,
        "profit": 7203.6861639318195,
        "win_rate": 0.47619047619047616
      },
      {
        "game": 127,
        "profit": 4258.8604473116375,
        "win_rate": 0.47244094488188976
      },
      {
        "game": 128,
        "profit": 1402.37950219006,
        "win_rate": 0.46875
      },
      {
        "game": 129,
        "profit": -1368.4070145778696,
        "win_rate": 0.46511627906976744
      },
      {
        "game": 130,
        "profit": 1319.2559066870222,
        "win_rate": 0.46923076923076923
      },
      {
        "game": 131,
        "profit": 3718.4430077361494,
        "win_rate": 0.4732824427480916
      },
      {
        "game": 132,
        "profit": 3618.4430077361494,
        "win_rate": 0.4696969696969697
      },
      {
        "game": 133,
        "profit": 3429.291779607195,
        "win_rate": 0.46616541353383456
      },
      {
        "game": 134,
        "profit": 3618.0647052798913,
        "win_rate": 0.4701492537313433
      },
      {
        "game": 135,
        "profit": 3518.0647052798913,
        "win_rate": 0.4666666666666667
      },
      {
        "game": 136,
        "profit": 3329.1142337558495,
        "win_rate": 0.4632352941176471
      },
      {
        "game": 137,
        "profit": 3517.686804336843,
        "win_rate": 0.46715328467153283
      },
      {
        "game": 138,
        "profit": 3328.7370886146873,
        "win_rate": 0.463768115942029
      },
      {
        "game": 139,
        "profit": 3517.308904905399,
        "win_rate": 0.4676258992805755
      },
      {
        "game": 140,
        "profit": 3716.324904905399,
        "win_rate": 0.4714285714285714
      },
      {
        "game": 141,
        "profit": 3816.324904905399,
        "win_rate": 0.475177304964539
      },
      {
        "game": 142,
        "profit": 4015.938936905399,
        "win_rate": 0.4788732394366197
      },
      {
        "game": 143,
        "profit": 3815.925676841399,
        "win_rate": 0.4755244755244755
      },
      {
        "game": 144,
        "profit": 3915.925676841399,
        "win_rate": 0.4791666666666667
      },
      {
        "game": 145,
        "profit": 3815.925676841399,
        "win_rate": 0.47586206896551725
      },
      {
        "game": 146,
        "profit": 3616.312443297527,
        "win_rate": 0.4726027397260274
      },
      {
        "game": 147,
        "profit": 3417.0984362207428,
        "win_rate": 0.46938775510204084
      },
      {
        "game": 148,
        "profit": 3517.0984362207428,
        "win_rate": 0.47297297297297297
      },
      {
        "game": 149,
        "profit": 3617.0984362207428,
        "win_rate": 0.47651006711409394
      },
      {
        "game": 150,
        "profit": 3417.882857158112,
        "win_rate": 0.47333333333333333
      },
      {
        "game": 151,
        "profit": 3517.882857158112,
        "win_rate": 0.4768211920529801
      },
      {
        "game": 152,
        "profit": 3318.865709253607,
        "win_rate": 0.47368421052631576
      },
      {
        "game": 153,
        "profit": 2921.627482036214,
        "win_rate": 0.47058823529411764
      },
      {
        "game": 154,
        "profit": -45.732517963785995,
        "win_rate": 0.4675324675324675
      },
      {
        "game": 155,
        "profit": -1484.9021179637862,
        "win_rate": 0.4645161290322581
      },
      {
        "game": 156,
        "profit": -2902.4841739637864,
        "win_rate": 0.46153846153846156
      },
      {
        "game": 157,
        "profit": -3002.4841739637864,
        "win_rate": 0.4585987261146497
      },
      {
        "game": 158,
        "profit": -2902.4841739637864,
        "win_rate": 0.4620253164556962
      },
      {
        "game": 159,
        "profit": -2802.4841739637864,
        "win_rate": 0.46540880503144655
      },
      {
        "game": 160,
        "profit": -2902.4841739637864,
        "win_rate": 0.4625
      },
      {
        "game": 161,
        "profit": -3002.4841739637864,
        "win_rate": 0.45962732919254656
      },
      {
        "game": 162,
        "profit": -3095.4720623077865,
        "win_rate": 0.4567901234567901
      },
      {
        "game": 163,
        "profit": -3395.4720623077865,
        "win_rate": 0.4539877300613497
      },
      {
        "game": 164,
        "profit": -3495.4720623077865,
        "win_rate": 0.45121951219512196
      },
      {
        "game": 165,
        "profit": -3595.4720623077865,
        "win_rate": 0.4484848484848485
      },
      {
        "game": 166,
        "profit": -3495.4720623077865,
        "win_rate": 0.45180722891566266
      },
      {
        "game": 167,
        "profit": -3794.6720623077863,
        "win_rate": 0.4491017964071856
      },
      {
        "game": 168,
        "profit": -4093.2736623077863,
        "win_rate": 0.44642857142857145
      },
      {
        "game": 169,
        "profit": -3795.2692655077863,
        "win_rate": 0.44970414201183434
      },
      {
        "game": 170,
        "profit": -3496.668859914186,
        "win_rate": 0.45294117647058824
      },
      {
        "game": 171,
        "profit": -3795.8664663189734,
        "win_rate": 0.4502923976608187
      },
      {
        "game": 172,
        "profit": -3695.8664663189734,
        "win_rate": 0.45348837209302323
      },
      {
        "game": 173,
        "profit": -3795.8664663189734,
        "win_rate": 0.4508670520231214
      },
      {
        "game": 174,
        "profit": -4094.465677510951,
        "win_rate": 0.4482758620689655
      },
      {
        "game": 175,
        "profit": -3796.463664741357,
        "win_rate": 0.4514285714285714
      },
      {
        "game": 176,
        "profit": -4095.06168153649,
        "win_rate": 0.44886363636363635
      },
      {
        "game": 177,
        "profit": -3499.060040013405,
        "win_rate": 0.4519774011299435
      },
      {
        "game": 178,
        "profit": -5892.602632370115,
        "win_rate": 0.449438202247191
      },
      {
        "game": 179,
        "profit": -10308.688715268247,
        "win_rate": 0.44692737430167595
      },
      {
        "game": 180,
        "profit": -14306.718648985356,
        "win_rate": 0.4444444444444444
      },
      {
        "game": 181,
        "profit": -18470.381251385028,
        "win_rate": 0.4419889502762431
      },
      {
        "game": 182,
        "profit": -14431.628527057344,
        "win_rate": 0.44505494505494503
      },
      {
        "game": 183,
        "profit": -14331.628527057344,
        "win_rate": 0.44808743169398907
      },
      {
        "game": 184,
        "profit": -14231.628527057344,
        "win_rate": 0.45108695652173914
      },
      {
        "game": 185,
        "profit": -14131.628527057344,
        "win_rate": 0.4540540540540541
      },
      {
        "game": 186,
        "profit": -14031.628527057344,
        "win_rate": 0.45698924731182794
      },
      {
        "game": 187,
        "profit": -14131.628527057344,
        "win_rate": 0.45454545454545453
      },
      {
        "game": 188,
        "profit": -14231.628527057344,
        "win_rate": 0.4521276595744681
      },
      {
        "game": 189,
        "profit": -14331.628527057344,
        "win_rate": 0.4497354497354497
      },
      {
        "game": 190,
        "profit": -14431.628527057344,
        "win_rate": 0.4473684210526316
      },
      {
        "game": 191,
        "profit": -14331.628527057344,
        "win_rate": 0.450261780104712
      },
      {
        "game": 192,
        "profit": -14431.628527057344,
        "win_rate": 0.4479166666666667
      },
      {
        "game": 193,
        "profit": -14531.628527057344,
        "win_rate": 0.44559585492227977
      },
      {
        "game": 194,
        "profit": -14631.628527057344,
        "win_rate": 0.44329896907216493
      },
      {
        "game": 195,
        "profit": -14731.628527057344,
        "win_rate": 0.441025641025641
      },
      {
        "game": 196,
        "profit": -14831.628527057344,
        "win_rate": 0.4387755102040816
      },
      {
        "game": 197,
        "profit": -14931.628527057344,
        "win_rate": 0.4365482233502538
      },
      {
        "game": 198,
        "profit": -15031.628527057344,
        "win_rate": 0.43434343434343436
      },
      {
        "game": 199,
        "profit": -14931.628527057344,
        "win_rate": 0.4371859296482412
      },
      {
        "game": 200,
        "profit": -15031.628527057344,
        "win_rate": 0.435
      },
      {
        "game": 201,
        "profit": -15307.756527057345,
        "win_rate": 0.43283582089552236
      },
      {
        "game": 202,
        "profit": -15583.332271057345,
        "win_rate": 0.4306930693069307
      },
      {
        "game": 203,
        "profit": -15858.356863569345,
        "win_rate": 0.42857142857142855
      },
      {
        "game": 204,
        "profit": -15583.882320242368,
        "win_rate": 0.43137254901960786
      },
      {
        "game": 205,
        "profit": -15308.858827828739,
        "win_rate": 0.43414634146341463
      },
      {
        "game": 206,
        "profit": -15584.432367227197,
        "win_rate": 0.4320388349514563
      },
      {
        "game": 207,
        "profit": -15684.432367227197,
        "win_rate": 0.42995169082125606
      },
      {
        "game": 208,
        "profit": -15584.432367227197,
        "win_rate": 0.4326923076923077
      },
      {
        "game": 209,
        "profit": -15684.432367227197,
        "win_rate": 0.430622009569378
      },
      {
        "game": 210,
        "profit": -15584.432367227197,
        "win_rate": 0.43333333333333335
      },
      {
        "game": 211,
        "profit": -15484.432367227197,
        "win_rate": 0.43601895734597157
      },
      {
        "game": 212,
        "profit": -15584.432367227197,
        "win_rate": 0.4339622641509434
      },
      {
        "game": 213,
        "profit": -15684.432367227197,
        "win_rate": 0.431924882629108
      },
      {
        "game": 214,
        "profit": -15584.432367227197,
        "win_rate": 0.43457943925233644
      },
      {
        "game": 215,
        "profit": -15684.432367227197,
        "win_rate": 0.4325581395348837
      },
      {
        "game": 216,
        "profit": -15584.432367227197,
        "win_rate": 0.4351851851851852
      },
      {
        "game": 217,
        "profit": -15684.432367227197,
        "win_rate": 0.43317972350230416
      },
      {
        "game": 218,
        "profit": -15389.609974907537,
        "win_rate": 0.43577981651376146
      },
      {
        "game": 219,
        "profit": -15094.197937803237,
        "win_rate": 0.4383561643835616
      },
      {
        "game": 220,
        "profit": -14798.19507662473,
        "win_rate": 0.4409090909090909
      },
      {
        "game": 221,
        "profit": -14698.19507662473,
        "win_rate": 0.4434389140271493
      },
      {
        "game": 222,
        "profit": -14798.19507662473,
        "win_rate": 0.44144144144144143
      },
      {
        "game": 223,
        "profit": -15094.789943525595,
        "win_rate": 0.43946188340807174
      },
      {
        "game": 224,
        "profit": -14994.789943525595,
        "win_rate": 0.4419642857142857
      },
      {
        "game": 225,
        "profit": -15094.789943525595,
        "win_rate": 0.44
      },
      {
        "game": 226,
        "profit": -14994.789943525595,
        "win_rate": 0.4424778761061947
      },
      {
        "game": 227,
        "profit": -15094.789943525595,
        "win_rate": 0.44052863436123346
      },
      {
        "game": 228,
        "profit": -15194.789943525595,
        "win_rate": 0.43859649122807015
      },
      {
        "game": 229,
        "profit": -15094.789943525595,
        "win_rate": 0.4410480349344978
      },
      {
        "game": 230,
        "profit": -14994.789943525595,
        "win_rate": 0.4434782608695652
      },
      {
        "game": 231,
        "profit": -14894.789943525595,
        "win_rate": 0.4458874458874459
      },
      {
        "game": 232,
        "profit": -14994.789943525595,
        "win_rate": 0.44396551724137934
      },
      {
        "game": 233,
        "profit": -14594.789943525595,
        "win_rate": 0.44635193133047213
      },
      {
        "game": 234,
        "profit": -14995.589943525594,
        "win_rate": 0.4444444444444444
      },
      {
        "game": 235,
        "profit": -15395.588343525595,
        "win_rate": 0.4425531914893617
      },
      {
        "game": 236,
        "profit": -15794.786746725595,
        "win_rate": 0.4406779661016949
      },
      {
        "game": 237,
        "profit": -16193.186753119195,
        "win_rate": 0.4388185654008439
      },
      {
        "game": 238,
        "profit": -15795.583546738382,
        "win_rate": 0.4411764705882353
      },
      {
        "game": 239,
        "profit": -14201.989895564084,
        "win_rate": 0.4435146443514644
      },
      {
        "game": 240,
        "profit": -15406.746695851853,
        "win_rate": 0.44166666666666665
      },
      {
        "game": 241,
        "profit": -18999.33147430998,
        "win_rate": 0.43983402489626555
      },
      {
        "game": 242,
        "profit": -15863.40413880253,
        "win_rate": 0.44214876033057854
      },
      {
        "game": 243,
        "profit": -19447.769083287545,
        "win_rate": 0.4403292181069959
      },
      {
        "game": 244,
        "profit": -25314.179709094686,
        "win_rate": 0.4385245901639344
      },
      {
        "game": 245,
        "profit": -31004.598016127613,
        "win_rate": 0.43673469387755104
      },
      {
        "game": 246,
        "profit": -25484.892258305674,
        "win_rate": 0.43902439024390244
      },
      {
        "game": 247,
        "profit": -31170.18918886227,
        "win_rate": 0.43724696356275305
      },
      {
        "game": 248,
        "profit": -25655.45116622237,
        "win_rate": 0.43951612903225806
      },
      {
        "game": 249,
        "profit": -31335.631329541466,
        "win_rate": 0.43775100401606426
      },
      {
        "game": 250,
        "profit": -36845.40608796099,
        "win_rate": 0.436
      },
      {
        "game": 251,
        "profit": -42189.887603627925,
        "win_rate": 0.4342629482071713
      },
      {
        "game": 252,
        "profit": -37005.740533430995,
        "win_rate": 0.4365079365079365
      },
      {
        "game": 253,
        "profit": -41277.477719273265,
        "win_rate": 0.43478260869565216
      },
      {
        "game": 254,
        "profit": -36065.9583525457,
        "win_rate": 0.43700787401574803
      }
    ]
  },
  "round_bet_amount": null
}